Coinpaprika/Client.py
Coinpaprika/Coinpaprika.py
Coinpaprika/CoinpaprikaCoin.py
Coinpaprika/CoinpaprikaExchanges.py
Coinpaprika/CoinpaprikaPeople.py
Coinpaprika/CoinpaprikaTags.py
Coinpaprika/CoinpaprikaTickers.py
Coinpaprika/__init__.py
coinpaprika_client-1.1.2.dist-info/LICENSE
coinpaprika_client-1.1.2.dist-info/METADATA
coinpaprika_client-1.1.2.dist-info/WHEEL
coinpaprika_client-1.1.2.dist-info/top_level.txt
coinpaprika_client-1.1.2.dist-info/RECORD
