Metadata-Version: 2.1
Name: coinpaprika-client
Version: 1.1.2
Summary: Coinpaprika API client written in Python
Home-page: https://coinpaper.io
Author: coinpaper.io
Author-email: contact@coinpaper.io
License: UNKNOWN
Project-URL: Coinpaprika API, https://api.coinpaprika.com
Project-URL: Coinpaper.io, https://coinpaper.io
Project-URL: Source Code, https://github.com/coinpaper/coinpaprika-api-python-client
Keywords: coinpaprika,api,wrapper,client,python
Platform: UNKNOWN
Classifier: Development Status :: 5 - Production/Stable
Classifier: Intended Audience :: Developers
Classifier: Topic :: Software Development :: Build Tools
Classifier: Programming Language :: Python :: 3
Classifier: Programming Language :: Python :: 3.6
Classifier: Programming Language :: Python :: 3.7
Classifier: Programming Language :: Python :: 3.8
Classifier: Programming Language :: Python :: 3.9
Classifier: Programming Language :: Python :: 3 :: Only
Classifier: License :: OSI Approved :: MIT License
Classifier: Operating System :: OS Independent
Requires-Python: >=3.6
Requires-Dist: requests
